oddasr/README.en.md
oddasr/README.md
oddasr/__init__.py
oddasr/app.py
oddasr/auth.json
oddasr/compile.py
oddasr/config.json
oddasr/log.py
oddasr/odd_asr_app.py
oddasr/odd_asr_config.py
oddasr/oddasr.db
oddasr/requirements.txt
oddasr/testAPI.py
oddasr/testLocal.py
oddasr/testStreamAPI.py
oddasr/testStreamLocal.py
oddasr/docs/README.en.md
oddasr/docs/README.md
oddasr/docs/oddasr-logo.svg
oddasr/docs/oddasr.png
oddasr/logic/__init__.py
oddasr/logic/hotwords.py
oddasr/logic/minutes.py
oddasr/logic/odd_asr_exceptions.py
oddasr/logic/odd_asr_file.py
oddasr/logic/odd_asr_instance.py
oddasr/logic/odd_asr_result.py
oddasr/logic/odd_asr_sentence.py
oddasr/logic/odd_asr_stream.py
oddasr/logic/odd_slp_server.py
oddasr/logic/odd_wss_server.py
oddasr/logic/proto.py
oddasr/logic/scheduled_task.py
oddasr/logic/sensitivewords.py
oddasr/logic/sensitivewords_opensdk.py
oddasr/logic/users.py
oddasr/logic/utils_speech.py
oddasr/model/__init__.py
oddasr/model/db.py
oddasr/model/hotword.py
oddasr/model/meeting.py
oddasr/model/sensitiveword.py
oddasr/model/text.py
oddasr/router/__init__.py
oddasr/router/asr_api.py
oddasr/router/asr_front.py
oddasr/router/front.py
oddasr/router/oddasr_session.py
oddasr/scripts/__init__.py
oddasr/scripts/update_table.py
oddasr/static/login.html
oddasr/static/common/bootstrap.min.css
oddasr/static/common/bootstrap.min.js
oddasr/static/common/crypto-js.js
oddasr/static/common/jquery.slim.min.js
oddasr/static/common/oddasr.js
oddasr/static/common/oddrecoder.js
oddasr/static/common/popper.min.js
oddasr/static/common/xlsx.core.min.js
oddasr/static/common/css/hotwords.css
oddasr/static/common/css/iconfont.css
oddasr/static/common/css/user_pwd.css
oddasr/static/common/css/images/all2.png
oddasr/static/common/css/images/capitals-tip.png
oddasr/static/common/css/images/myicon.png
oddasr/static/common/css/images/setting.png
oddasr/static/common/css/images/sprite_all.png
oddasr/static/common/js/hotwords.js
oddasr/static/common/js/user_pwd.js
oddasr-0.6.10.dist-info/licenses/LICENSE
oddasr-0.6.10.dist-info/METADATA
oddasr-0.6.10.dist-info/WHEEL
oddasr-0.6.10.dist-info/entry_points.txt
oddasr-0.6.10.dist-info/top_level.txt
oddasr-0.6.10.dist-info/RECORD
