Metadata-Version: 2.4
Name: oddasr
Version: 0.6.10
Summary: An ASR API server for FunASR
Author-email: Catherine Wei <catherine@oddmeta.com>, Jacky Wei <jacky@oddmeta.com>
License-Expression: MIT
Project-URL: Homepage, https://oddmeta.net/oddasr
Project-URL: Repository, https://github.com/oddmeta/oddasr
Project-URL: Issues, https://github.com/oddmeta/oddasr/issues
Classifier: Programming Language :: Python :: 3
Classifier: Operating System :: OS Independent
Requires-Python: >=3.10
License-File: LICENSE
Requires-Dist: Flask==3.1.1
Requires-Dist: funasr==1.3.0
Requires-Dist: librosa==0.11.0
Requires-Dist: torch==2.7.0
Requires-Dist: torchaudio==2.7.0
Requires-Dist: addict==2.4.0
Requires-Dist: modelscope==1.9.5
Requires-Dist: datasets==2.12.0
Requires-Dist: requests==2.31.0
Requires-Dist: Werkzeug==3.1.3
Requires-Dist: flask_cors==4.0.1
Requires-Dist: python-dotenv==1.0.0
Requires-Dist: websockets==15.0.1
Requires-Dist: mutagen==1.47.0
Requires-Dist: sqlalchemy==2.0.25
Requires-Dist: redis==5.0.1
Dynamic: license-file
